MANIFEST.in
README.md
setup.cfg
setup.py
drf_request_logging/__init__.py
drf_request_logging/admin.py
drf_request_logging/apps.py
drf_request_logging/enums.py
drf_request_logging/exceptions.py
drf_request_logging/masks.py
drf_request_logging/mixins.py
drf_request_logging/models.py
drf_request_logging.egg-info/PKG-INFO
drf_request_logging.egg-info/SOURCES.txt
drf_request_logging.egg-info/dependency_links.txt
drf_request_logging.egg-info/requires.txt
drf_request_logging.egg-info/top_level.txt
drf_request_logging/migrations/0001_initial.py
drf_request_logging/migrations/0002_auto_20200124_1348.py
drf_request_logging/migrations/0003_auto_20200304_1321.py
drf_request_logging/migrations/0004_auto_20200821_1433.py
drf_request_logging/migrations/0005_auto_20201211_1549.py
drf_request_logging/migrations/0006_auto_20210604_1311.py
drf_request_logging/migrations/__init__.py